{
  "participantId": "P1748341389741-7587",
  "demographicInfo": {
    "age": "18-21",
    "gender": "female",
    "musicalBackground": "beginner",
    "theory": "basic",
    "listenFrequency": "everyweek",
    "liveFrequency": "weekly",
    "listeningEnvironment": "laptop-headphones-outdoor",
    "participantId": "",
    "experimentStartTime": "2025-05-27T10:23:09.741Z"
  },
  "stimuli": [
    {
      "stimulusIndex": 1,
      "genre": "jazz",
      "song_id": "jazz_s3",
      "segment_type": "start",
      "likeRating": 4,
      "complexRating": 4,
      "familiarRating": 4,
      "structureRating": "5",
      "emotionRating": "1",
      "engagementRating": 4,
      "selectedComponent": "melody",
      "genreSelection": "pop_dance",
      "curiosityRating": 2,
      "totalPlayCount": 2,
      "questionStartTime": "2025-05-27T10:23:09.815Z",
      "questionEndTime": "2025-05-27T10:23:48.034Z",
      "questionDurationMs": 38219
    },
    {
      "stimulusIndex": 2,
      "genre": "math_rock",
      "song_id": "math_rock_s4",
      "segment_type": "mid",
      "likeRating": 4,
      "complexRating": 4,
      "familiarRating": 4,
      "structureRating": "1",
      "emotionRating": "5",
      "engagementRating": 4,
      "selectedComponent": "rhythm",
      "genreSelection": "citypop",
      "curiosityRating": 4,
      "totalPlayCount": 1,
      "questionStartTime": "2025-05-27T10:23:48.034Z",
      "questionEndTime": "2025-05-27T10:24:31.288Z",
      "questionDurationMs": 43254
    },
    {
      "stimulusIndex": 3,
      "genre": "classical",
      "song_id": "classical_s2",
      "segment_type": "start",
      "likeRating": 4,
      "complexRating": 4,
      "familiarRating": 4,
      "structureRating": "2",
      "emotionRating": "2",
      "engagementRating": 4,
      "selectedComponent": "harmony",
      "genreSelection": "citypop",
      "curiosityRating": 4,
      "totalPlayCount": 1,
      "questionStartTime": "2025-05-27T10:24:31.288Z",
      "questionEndTime": "2025-05-27T10:25:12.262Z",
      "questionDurationMs": 40974
    }
  ],
  "experimentSummary": {
    "experimentStartTime": "2025-05-27T10:23:09.741Z",
    "experimentEndTime": "2025-05-27T10:25:12.263Z",
    "totalExperimentDurationMs": 122522,
    "totalExperimentDurationMin": "2.04",
    "totalStimuliCompleted": 3,
    "playStatistics": {
      "totalPlays": 4,
      "averagePlaysPerStimulus": "1.33",
      "maxPlaysForAnyStimulus": 2,
      "minPlaysForAnyStimulus": 1
    },
    "averageQuestionTimeMs": "40816",
    "averageQuestionTimeSec": "40.82"
  }
}